graffitiai/__init__.py
graffitiai/base.py
graffitiai/christine.py
graffitiai/conjecture_class.py
graffitiai/graffiti.py
graffitiai/graffitiai.py
graffitiai/heuristics.py
graffitiai/models.py
graffitiai/optimization.py
graffitiai/txgraffiti.py
graffitiai/utils.py
graffitiai/data/data_4215.csv
graffitiai/data/data_437.csv
graffitiai/data/graph_data.csv
graffitiai/data/sample_3_regular_polytope_data.csv
graffitiai/experimental/__init__.py
graffitiai/experimental/candidate_operations.py
graffitiai/experimental/candidate_transformations.py
graffitiai/experimental/expression_generator.py
graffitiai/experimental/expression_objects.py
graffitiai/experimental/graffiti.py
graffitiai/experimental/legacy_graffiti.py
graffitiai/experimental/models.py
graffitiai/experimental/optimist.py
graffitiai/experimental/utils.py
graffitiai-0.1.19.dist-info/LICENSE
graffitiai-0.1.19.dist-info/METADATA
graffitiai-0.1.19.dist-info/WHEEL
graffitiai-0.1.19.dist-info/top_level.txt
graffitiai-0.1.19.dist-info/RECORD
