Metadata-Version: 2.1
Name: graffitiai
Version: 0.1.19
Summary: A Python package for automated mathematical conjecturing.
Home-page: https://github.com/RandyRDavila/GraffitiAI
Author: Randy Davila
Author-email: randyrdavila@gmail.com
License: MIT
Classifier: Programming Language :: Python :: 3
Classifier: License :: OSI Approved :: MIT License
Classifier: Operating System :: OS Independent
Requires-Python: >=3.7
License-File: LICENSE
Requires-Dist: numpy
Requires-Dist: pandas
Requires-Dist: reportlab
Requires-Dist: PuLP
Requires-Dist: tqdm
Requires-Dist: pyfiglet
